opengraph_parse/__init__.py
opengraph_parse/example.py
opengraph_parse/opengraph_parse.py
opengraph_parse-0.0.6.dist-info/LICENSE
opengraph_parse-0.0.6.dist-info/METADATA
opengraph_parse-0.0.6.dist-info/WHEEL
opengraph_parse-0.0.6.dist-info/top_level.txt
opengraph_parse-0.0.6.dist-info/RECORD
