Metadata-Version: 2.1
Name: opengraph-parse
Version: 0.0.6
Summary: Parses Open Graph meta tags of web pages and returns a handy JSON-like object. Use this to generate preview of web pages like you see on social media
Home-page: https://github.com/ben-jacobson/opengraph_parse
Author: Ben Jacobson
Author-email: 
License: UNKNOWN
Platform: UNKNOWN
Classifier: Programming Language :: Python :: 3
Classifier: License :: OSI Approved :: MIT License
Classifier: Operating System :: OS Independent
Requires-Python: >=3.6
Requires-Dist: bs4
Requires-Dist: requests
